{
  "last_audited_commit": "32dc14872db6a9b8a9ee96dd5ebcdc4f2e8f7a29",
  "rules_fingerprint": "sha256:c319b129e6c2fb3dbf7e7d017a5b4f2c8ca9b37e697199b969f5cbb681258785",
  "plugin_version": "0.25.2",
  "configured_by": "SmithDR",
  "configured_at": "2026-06-17",
  "schema_version": 1,
  "reviewed_rules": [
    "architecture-coherence",
    "as-const-opportunity",
    "duplicate-literal-union",
    "feature-deps",
    "file-responsibility",
    "folder-placement",
    "forbidden-imports",
    "hardcoded-data",
    "inline-shape-extract",
    "layer-boundaries",
    "magic-literal-repeated",
    "prefer-as-const",
    "prefer-branded-type",
    "prefer-discriminated-union",
    "prefer-satisfies",
    "repeated-object-shape",
    "schema-type-redeclare",
    "secrets",
    "server-client-boundaries",
    "stringly-typed",
    "tailwind-arbitrary-has-token",
    "tailwind-arbitrary-values",
    "tailwind-classname-bloat",
    "tailwind-conditional-concat",
    "tailwind-duplicate-utilities",
    "tailwind-off-theme-value",
    "tsconfig-strictness",
    "type-duplicate-shape",
    "untranslated-text"
  ]
}
